odoo/addons/contract_sale_invoicing/README.rst
odoo/addons/contract_sale_invoicing/__init__.py
odoo/addons/contract_sale_invoicing/__manifest__.py
odoo/addons/contract_sale_invoicing/i18n/es.po
odoo/addons/contract_sale_invoicing/models/__init__.py
odoo/addons/contract_sale_invoicing/models/contract.py
odoo/addons/contract_sale_invoicing/static/description/icon.png
odoo/addons/contract_sale_invoicing/tests/__init__.py
odoo/addons/contract_sale_invoicing/tests/test_contract_sale_invoicing.py
odoo/addons/contract_sale_invoicing/views/contract_view.xml
odoo11_addon_contract_sale_invoicing-11.0.1.0.0.dist-info/DESCRIPTION.rst
odoo11_addon_contract_sale_invoicing-11.0.1.0.0.dist-info/METADATA
odoo11_addon_contract_sale_invoicing-11.0.1.0.0.dist-info/RECORD
odoo11_addon_contract_sale_invoicing-11.0.1.0.0.dist-info/WHEEL
odoo11_addon_contract_sale_invoicing-11.0.1.0.0.dist-info/metadata.json
odoo11_addon_contract_sale_invoicing-11.0.1.0.0.dist-info/top_level.txt
